perivale/__init__.py
perivale/buffer.py
perivale/errors.py
perivale/excerpt.py
perivale/position.py
perivale/helpers/__init__.py
perivale/helpers/in_range.py
perivale/helpers/parse_escape_code.py
perivale/helpers/parse_identifier.py
perivale/helpers/parse_integer.py
perivale-1.1.14.dist-info/LICENSE
perivale-1.1.14.dist-info/METADATA
perivale-1.1.14.dist-info/WHEEL
perivale-1.1.14.dist-info/top_level.txt
perivale-1.1.14.dist-info/RECORD
