Metadata-Version: 2.1
Name: perivale
Version: 1.1.14
Summary: A text navigation parse buffer
Home-page: https://github.com/inigo-selwood/perivale
Author: Inigo Selwood
Author-email: inigo.selwood@outlook.com
Project-URL: Bug Tracker, https://github.com/inigo-selwood/perivale/issues
Classifier: Programming Language :: Python :: 3
Classifier: License :: OSI Approved :: MIT License
Classifier: Operating System :: OS Independent
Requires-Python: >=3.6
License-File: LICENSE
